MailReader/__init__.py
robotframework_mailreader-1.0.0.dist-info/METADATA
robotframework_mailreader-1.0.0.dist-info/WHEEL
robotframework_mailreader-1.0.0.dist-info/top_level.txt
robotframework_mailreader-1.0.0.dist-info/RECORD
