Metadata-Version: 2.1
Name: robotframework-mailreader
Version: 1.0.0
Summary: Send and read mails using Robot Framework.
Home-page: https://github.com/arvindmehairjan/robotframework_mailreader
Author: Arvind Mehairjan
Author-email: 
License: MIT
Platform: UNKNOWN
Classifier: License :: OSI Approved :: MIT License
Classifier: Programming Language :: Python :: 3
Classifier: Programming Language :: Python :: 3.6
Classifier: Programming Language :: Python :: 3.7
Classifier: Programming Language :: Python :: 3.8
Classifier: Programming Language :: Python :: 3.9
Requires-Dist: imaplib
Requires-Dist: robotframework (==3.2.2)
Requires-Dist: robotframework-pythonlibcore (==2.2.1)
Requires-Dist: smtplib
Requires-Dist: email
